pysideprocessing/__about__.py
pysideprocessing/color.py
pysideprocessing/papplet.py
pysideprocessing/pconstants.py
pysideprocessing/pgraphics.py
pysideprocessing/pimage.py
pysideprocessing/pwidget.py
pysideprocessing/py.typed
pysideprocessing-0.0.12.dist-info/METADATA
pysideprocessing-0.0.12.dist-info/WHEEL
pysideprocessing-0.0.12.dist-info/licenses/LICENSE
pysideprocessing-0.0.12.dist-info/RECORD
